slackinformer/__init__.py
slackinformer/slackinformer.py
slackinformer-0.0.2.dist-info/LICENSE
slackinformer-0.0.2.dist-info/METADATA
slackinformer-0.0.2.dist-info/WHEEL
slackinformer-0.0.2.dist-info/top_level.txt
slackinformer-0.0.2.dist-info/RECORD
