Metadata-Version: 2.1
Name: slackinformer
Version: 0.0.2
Summary: Informs Slack for sth.
Home-page: https://github.com/blgnksy/slackinformer/
Author: Fatih Baltacı
Author-email: baltacifatih14@gmail.com
License: UNKNOWN
Platform: UNKNOWN
Classifier: Programming Language :: Python :: 3.7
Classifier: License :: OSI Approved :: GNU General Public License v3 (GPLv3)
Requires-Dist: slackclient
